fatbotslim
