Metadata-Version: 1.1
Name: FatBotSlim
Version: 0.2
Summary: Yet another IRC bot library
Home-page: http://mattoufoutu.github.com/fatbotslim
Author: Mathieu D. (MatToufoutu)
Author-email: mattoufootu@gmail.com
License: GPL
Keywords: irc ircbot bot
Platform: UNKNOWN
Classifier: Development Status :: 5 - Production/Stable
Classifier: Environment :: Console
Classifier: Environment :: Plugins
Classifier: Intended Audience :: Developers
Classifier: Intended Audience :: End Users/Desktop
Classifier: License :: OSI Approved :: GNU General Public License (GPL)
Classifier: Programming Language :: Python :: 2.7
Classifier: Topic :: Communications :: Chat :: Internet Relay Chat
Classifier: Topic :: Internet
